alpha_vantage_downloader/__init__.py
alpha_vantage_downloader/config.py
alpha_vantage_downloader/downloader.py
alpha_vantage_downloader-0.0.5.dist-info/METADATA
alpha_vantage_downloader-0.0.5.dist-info/RECORD
alpha_vantage_downloader-0.0.5.dist-info/WHEEL
alpha_vantage_downloader-0.0.5.dist-info/top_level.txt
